{
    "allocation_quality": 250.99998474121094,
    "solution": {
        "allocation": [
            [
                1.0,
                1.0,
                1.0
            ],
            [
                1.0,
                1.0,
                1.0
            ],
            [
                0.0,
                1.0,
                0.0
            ],
            [
                1.0,
                1.0,
                1.0
            ],
            [
                1.0,
                1.0,
                0.0
            ],
            [
                1.0,
                1.0,
                1.0
            ]
        ],
        "makespan": 91.37376403808594,
        "precedence_constraints": [
            [
                2,
                3
            ]
        ],
        "precedence_set_mutex_constraints": [
            [
                1,
                0
            ],
            [
                3,
                0
            ],
            [
                2,
                0
            ],
            [
                5,
                1
            ],
            [
                5,
                0
            ],
            [
                2,
                1
            ],
            [
                5,
                4
            ],
            [
                3,
                1
            ],
            [
                4,
                0
            ],
            [
                1,
                4
            ],
            [
                2,
                4
            ],
            [
                2,
                5
            ],
            [
                3,
                5
            ],
            [
                3,
                4
            ]
        ],
        "robots": [
            {
                "id": 0,
                "individual_plan": [
                    3,
                    5,
                    1,
                    4,
                    0
                ],
                "name": "Ambulance0",
                "transitions": [
                    {
                        "path": [
                            {
                                "configuration_type": "ompl",
                                "goal_type": "state",
                                "state_space_type": "se2",
                                "x": 20.97500228881836,
                                "y": -7.024998188018799,
                                "yaw": 0.0
                            },
                            {
                                "configuration_type": "ompl",
                                "goal_type": "state",
                                "state_space_type": "se2",
                                "x": -37.42499923706055,
                                "y": 22.375001907348633,
                                "yaw": 0.0
                            }
                        ],
                        "path_length": 65.38287353515625
                    },
                    {
                        "path": [
                            {
                                "configuration_type": "ompl",
                                "goal_type": "state",
                                "state_space_type": "se2",
                                "x": -36.82499694824219,
                                "y": -39.57499694824219,
                                "yaw": 0.0
                            },
                            {
                                "configuration_type": "ompl",
                                "goal_type": "state",
                                "state_space_type": "se2",
                                "x": -36.82499694824219,
                                "y": -39.57499694824219,
                                "yaw": 0.0
                            }
                        ],
                        "path_length": 0.0
                    },
                    {
                        "path": [
                            {
                                "configuration_type": "ompl",
                                "goal_type": "state",
                                "state_space_type": "se2",
                                "x": -24.674997329711914,
                                "y": -40.624996185302734,
                                "yaw": 0.0
                            },
                            {
                                "configuration_type": "ompl",
                                "goal_type": "state",
                                "state_space_type": "se2",
                                "x": -24.674997329711914,
                                "y": -40.624996185302734,
                                "yaw": 0.0
                            }
                        ],
                        "path_length": 0.0
                    },
                    {
                        "path": [
                            {
                                "configuration_type": "ompl",
                                "goal_type": "state",
                                "state_space_type": "se2",
                                "x": 28.17500114440918,
                                "y": -19.32499885559082,
                                "yaw": 0.0
                            },
                            {
                                "configuration_type": "ompl",
                                "goal_type": "state",
                                "state_space_type": "se2",
                                "x": 28.17500114440918,
                                "y": -19.32499885559082,
                                "yaw": 0.0
                            }
                        ],
                        "path_length": 0.0
                    },
                    {
                        "path": [
                            {
                                "configuration_type": "ompl",
                                "goal_type": "state",
                                "state_space_type": "se2",
                                "x": 32.275001525878906,
                                "y": -50.77499771118164,
                                "yaw": 0.0
                            },
                            {
                                "configuration_type": "ompl",
                                "goal_type": "state",
                                "state_space_type": "se2",
                                "x": 32.275001525878906,
                                "y": -50.77499771118164,
                                "yaw": 0.0
                            }
                        ],
                        "path_length": 0.0
                    }
                ]
            },
            {
                "id": 1,
                "individual_plan": [
                    2,
                    3,
                    5,
                    1,
                    4,
                    0
                ],
                "name": "FireTruckGround0",
                "transitions": [
                    {
                        "path": [
                            {
                                "configuration_type": "ompl",
                                "goal_type": "state",
                                "state_space_type": "se2",
                                "x": -21.174997329711914,
                                "y": 12.375001907348633,
                                "yaw": 0.0
                            },
                            {
                                "configuration_type": "ompl",
                                "goal_type": "state",
                                "state_space_type": "se2",
                                "x": -38.57499694824219,
                                "y": -7.824997901916504,
                                "yaw": 0.0
                            }
                        ],
                        "path_length": 26.660831451416016
                    },
                    {
                        "path": [
                            {
                                "configuration_type": "ompl",
                                "goal_type": "state",
                                "state_space_type": "se2",
                                "x": -37.42499923706055,
                                "y": 22.375001907348633,
                                "yaw": 0.0
                            },
                            {
                                "configuration_type": "ompl",
                                "goal_type": "state",
                                "state_space_type": "se2",
                                "x": -37.42499923706055,
                                "y": 22.375001907348633,
                                "yaw": 0.0
                            }
                        ],
                        "path_length": 0.0
                    },
                    {
                        "path": [
                            {
                                "configuration_type": "ompl",
                                "goal_type": "state",
                                "state_space_type": "se2",
                                "x": -36.82499694824219,
                                "y": -39.57499694824219,
                                "yaw": 0.0
                            },
                            {
                                "configuration_type": "ompl",
                                "goal_type": "state",
                                "state_space_type": "se2",
                                "x": -36.82499694824219,
                                "y": -39.57499694824219,
                                "yaw": 0.0
                            }
                        ],
                        "path_length": 0.0
                    },
                    {
                        "path": [
                            {
                                "configuration_type": "ompl",
                                "goal_type": "state",
                                "state_space_type": "se2",
                                "x": -24.674997329711914,
                                "y": -40.624996185302734,
                                "yaw": 0.0
                            },
                            {
                                "configuration_type": "ompl",
                                "goal_type": "state",
                                "state_space_type": "se2",
                                "x": -24.674997329711914,
                                "y": -40.624996185302734,
                                "yaw": 0.0
                            }
                        ],
                        "path_length": 0.0
                    },
                    {
                        "path": [
                            {
                                "configuration_type": "ompl",
                                "goal_type": "state",
                                "state_space_type": "se2",
                                "x": 28.17500114440918,
                                "y": -19.32499885559082,
                                "yaw": 0.0
                            },
                            {
                                "configuration_type": "ompl",
                                "goal_type": "state",
                                "state_space_type": "se2",
                                "x": 28.17500114440918,
                                "y": -19.32499885559082,
                                "yaw": 0.0
                            }
                        ],
                        "path_length": 0.0
                    },
                    {
                        "path": [
                            {
                                "configuration_type": "ompl",
                                "goal_type": "state",
                                "state_space_type": "se2",
                                "x": 32.275001525878906,
                                "y": -50.77499771118164,
                                "yaw": 0.0
                            },
                            {
                                "configuration_type": "ompl",
                                "goal_type": "state",
                                "state_space_type": "se2",
                                "x": 32.275001525878906,
                                "y": -50.77499771118164,
                                "yaw": 0.0
                            }
                        ],
                        "path_length": 0.0
                    }
                ]
            },
            {
                "id": 2,
                "individual_plan": [
                    3,
                    5,
                    1,
                    0
                ],
                "name": "CraneGround0",
                "transitions": [
                    {
                        "path": [
                            {
                                "configuration_type": "ompl",
                                "goal_type": "state",
                                "state_space_type": "se2",
                                "x": -45.07499694824219,
                                "y": 38.72500228881836,
                                "yaw": 0.0
                            },
                            {
                                "configuration_type": "ompl",
                                "goal_type": "state",
                                "state_space_type": "se2",
                                "x": -37.42499923706055,
                                "y": 22.375001907348633,
                                "yaw": 0.0
                            }
                        ],
                        "path_length": 18.051176071166992
                    },
                    {
                        "path": [
                            {
                                "configuration_type": "ompl",
                                "goal_type": "state",
                                "state_space_type": "se2",
                                "x": -36.82499694824219,
                                "y": -39.57499694824219,
                                "yaw": 0.0
                            },
                            {
                                "configuration_type": "ompl",
                                "goal_type": "state",
                                "state_space_type": "se2",
                                "x": -36.82499694824219,
                                "y": -39.57499694824219,
                                "yaw": 0.0
                            }
                        ],
                        "path_length": 0.0
                    },
                    {
                        "path": [
                            {
                                "configuration_type": "ompl",
                                "goal_type": "state",
                                "state_space_type": "se2",
                                "x": -24.674997329711914,
                                "y": -40.624996185302734,
                                "yaw": 0.0
                            },
                            {
                                "configuration_type": "ompl",
                                "goal_type": "state",
                                "state_space_type": "se2",
                                "x": -24.674997329711914,
                                "y": -40.624996185302734,
                                "yaw": 0.0
                            }
                        ],
                        "path_length": 0.0
                    },
                    {
                        "path": [
                            {
                                "configuration_type": "ompl",
                                "goal_type": "state",
                                "state_space_type": "se2",
                                "x": 32.275001525878906,
                                "y": -50.77499771118164,
                                "yaw": 0.0
                            },
                            {
                                "configuration_type": "ompl",
                                "goal_type": "state",
                                "state_space_type": "se2",
                                "x": 32.275001525878906,
                                "y": -50.77499771118164,
                                "yaw": 0.0
                            }
                        ],
                        "path_length": 0.0
                    }
                ]
            }
        ],
        "tasks": [
            {
                "coalition": [
                    0,
                    1,
                    2
                ],
                "execution_motion_plan": {
                    "path": [
                        {
                            "configuration_type": "ompl",
                            "goal_type": "state",
                            "state_space_type": "se2",
                            "x": 32.275001525878906,
                            "y": -50.77499771118164,
                            "yaw": 0.0
                        },
                        {
                            "configuration_type": "ompl",
                            "goal_type": "state",
                            "state_space_type": "se2",
                            "x": 32.275001525878906,
                            "y": -50.77499771118164,
                            "yaw": 0.0
                        }
                    ],
                    "path_length": 0.0
                },
                "finish_timepoint": 91.37376403808594,
                "id": 0,
                "name": "repairBuilding",
                "start_timepoint": 91.27376556396484
            },
            {
                "coalition": [
                    0,
                    1,
                    2
                ],
                "execution_motion_plan": {
                    "path": [
                        {
                            "configuration_type": "ompl",
                            "goal_type": "state",
                            "state_space_type": "se2",
                            "x": -24.674997329711914,
                            "y": -40.624996185302734,
                            "yaw": 0.0
                        },
                        {
                            "configuration_type": "ompl",
                            "goal_type": "state",
                            "state_space_type": "se2",
                            "x": -24.674997329711914,
                            "y": -40.624996185302734,
                            "yaw": 0.0
                        }
                    ],
                    "path_length": 0.0
                },
                "finish_timepoint": 61.608123779296875,
                "id": 1,
                "name": "clearRubble",
                "start_timepoint": 61.50812530517578
            },
            {
                "coalition": [
                    1
                ],
                "execution_motion_plan": {
                    "path": [
                        {
                            "configuration_type": "ompl",
                            "goal_type": "state",
                            "state_space_type": "se2",
                            "x": -38.57499694824219,
                            "y": -7.824997901916504,
                            "yaw": 0.0
                        },
                        {
                            "configuration_type": "ompl",
                            "goal_type": "state",
                            "state_space_type": "se2",
                            "x": -21.174997329711914,
                            "y": 12.375001907348633,
                            "yaw": 0.0
                        }
                    ],
                    "path_length": 26.660831451416016
                },
                "finish_timepoint": 17.87388801574707,
                "id": 2,
                "name": "exstinguishFire",
                "start_timepoint": 8.886943817138672
            },
            {
                "coalition": [
                    0,
                    1,
                    2
                ],
                "execution_motion_plan": {
                    "path": [
                        {
                            "configuration_type": "ompl",
                            "goal_type": "state",
                            "state_space_type": "se2",
                            "x": -37.42499923706055,
                            "y": 22.375001907348633,
                            "yaw": 0.0
                        },
                        {
                            "configuration_type": "ompl",
                            "goal_type": "state",
                            "state_space_type": "se2",
                            "x": -37.42499923706055,
                            "y": 22.375001907348633,
                            "yaw": 0.0
                        }
                    ],
                    "path_length": 0.0
                },
                "finish_timepoint": 24.334030151367188,
                "id": 3,
                "name": "repairBuilding",
                "start_timepoint": 24.23402976989746
            },
            {
                "coalition": [
                    0,
                    1
                ],
                "execution_motion_plan": {
                    "path": [
                        {
                            "configuration_type": "ompl",
                            "goal_type": "state",
                            "state_space_type": "se2",
                            "x": 28.17500114440918,
                            "y": -19.32499885559082,
                            "yaw": 0.0
                        },
                        {
                            "configuration_type": "ompl",
                            "goal_type": "state",
                            "state_space_type": "se2",
                            "x": 28.17500114440918,
                            "y": -19.32499885559082,
                            "yaw": 0.0
                        }
                    ],
                    "path_length": 0.0
                },
                "finish_timepoint": 80.70172119140625,
                "id": 4,
                "name": "repairBuilding",
                "start_timepoint": 80.60172271728516
            },
            {
                "coalition": [
                    0,
                    1,
                    2
                ],
                "execution_motion_plan": {
                    "path": [
                        {
                            "configuration_type": "ompl",
                            "goal_type": "state",
                            "state_space_type": "se2",
                            "x": -36.82499694824219,
                            "y": -39.57499694824219,
                            "yaw": 0.0
                        },
                        {
                            "configuration_type": "ompl",
                            "goal_type": "state",
                            "state_space_type": "se2",
                            "x": -36.82499694824219,
                            "y": -39.57499694824219,
                            "yaw": 0.0
                        }
                    ],
                    "path_length": 0.0
                },
                "finish_timepoint": 55.41048049926758,
                "id": 5,
                "name": "clearRubble",
                "start_timepoint": 55.310482025146484
            }
        ]
    },
    "statistics": {
        "motion_planning_time": 0.3446105718612671,
        "nodes_deadend": 0,
        "nodes_evaluated": 51,
        "nodes_expanded": 3,
        "nodes_generated": 52,
        "nodes_pruned": 0,
        "nodes_reopened": 0,
        "num_motion_plan_failures": 0,
        "num_motion_plans": 68,
        "num_scheduling_failures": 0,
        "num_scheduling_iterations": 248,
        "scheduling_time": 0.8283846378326416,
        "task_allocation_time": 0.01931285858154297,
        "total_time": 1.1923080682754517
    }
}
